yz_openai/__init__.py
yz_openai/client.py
yz_openai/factory.py
yz_openai/base/__init__.py
yz_openai/base/exceptions.py
yz_openai/base/types.py
yz_openai/base/utils.py
yz_openai/providers/__init__.py
yz_openai/providers/litellm/__init__.py
yz_openai/providers/litellm/chat.py
yz_openai/providers/volcengine/__init__.py
yz_openai/providers/volcengine/asr.py
yz_openai/providers/volcengine/auc_websocket_demo.py
yz_openai/providers/volcengine/chat.py
yz_openai/providers/volcengine/podcast.py
yz_openai/providers/volcengine/sauc_websocket_demo.py
yz_openai/providers/volcengine/tts.py
yz_openai/providers/volcengine/websocket_protocol.py
yz_openai-0.1.5.dist-info/licenses/LICENSE
yz_openai-0.1.5.dist-info/METADATA
yz_openai-0.1.5.dist-info/WHEEL
yz_openai-0.1.5.dist-info/top_level.txt
yz_openai-0.1.5.dist-info/RECORD
