Metadata-Version: 2.4
Name: yz-openai
Version: 0.1.5
Summary: 有赞 LLM 统一调用库
Author-email: YouzanTech <tech@youzan.com>
License: MIT
Project-URL: Homepage, https://github.com/youzan/yz-openai
Project-URL: Documentation, https://github.com/youzan/yz-openai/blob/main/README.md
Project-URL: Repository, https://github.com/youzan/yz-openai.git
Project-URL: Issues, https://github.com/youzan/yz-openai/issues
Keywords: llm,openai,chatgpt,ai,youzan,podcast,tts
Classifier: Development Status :: 3 - Alpha
Classifier: Intended Audience :: Developers
Classifier: License :: OSI Approved :: MIT License
Classifier: Programming Language :: Python :: 3
Classifier: Programming Language :: Python :: 3.8
Classifier: Programming Language :: Python :: 3.9
Classifier: Programming Language :: Python :: 3.10
Classifier: Programming Language :: Python :: 3.11
Classifier: Programming Language :: Python :: 3.12
Requires-Python: >=3.8
License-File: LICENSE
Requires-Dist: httpx>=0.24.0
Requires-Dist: litellm>=1.0.0
Requires-Dist: openai>=1.0.0
Requires-Dist: websockets>=12.0
Requires-Dist: volcengine-python-sdk[ark]>=1.0.0
Provides-Extra: dev
Requires-Dist: pytest>=7.0.0; extra == "dev"
Requires-Dist: pytest-asyncio>=0.21.0; extra == "dev"
Requires-Dist: pytest-cov>=4.0.0; extra == "dev"
Requires-Dist: black>=23.0.0; extra == "dev"
Requires-Dist: flake8>=6.0.0; extra == "dev"
Requires-Dist: mypy>=1.0.0; extra == "dev"
Dynamic: license-file
